anagram/__init__.py
anagram/anagram.py
anagram-0.0.2.dist-info/DESCRIPTION.rst
anagram-0.0.2.dist-info/METADATA
anagram-0.0.2.dist-info/RECORD
anagram-0.0.2.dist-info/WHEEL
anagram-0.0.2.dist-info/entry_points.txt
anagram-0.0.2.dist-info/metadata.json
anagram-0.0.2.dist-info/top_level.txt
