Metadata-Version: 2.0
Name: anagram
Version: 0.0.2
Summary: I'm a small script that help you get anagram use wordsmith.org.
Home-page: https://github.com/RayYu03/anagram
Author: RayYu03
Author-email: shiliuhuasheng@gmail.com
License: MIT
Keywords: anagram,generate,game
Platform: UNKNOWN
Classifier: Development Status :: 3 - Alpha
Classifier: Environment :: Web Environment
Classifier: Intended Audience :: Information Technology
Classifier: Intended Audience :: End Users/Desktop
Classifier: License :: OSI Approved :: MIT License
Classifier: Operating System :: OS Independent
Classifier: Programming Language :: Python
Classifier: Topic :: Internet :: WWW/HTTP
Requires-Dist: beautifulsoup4
Requires-Dist: requests
